{
    "uuid": [
        {
            "value": "9b54e3f2-e1ab-43d1-98fa-6fd146966eba"
        }
    ],
    "langcode": [
        {
            "value": "en"
        }
    ],
    "uid": [
        {
            "target_type": "user",
            "target_uuid": "d6eb66d1-cfff-40d6-a130-ca95762489a0"
        }
    ],
    "filename": [
        {
            "value": "photo_2020-06-05 19.31.47.jpeg"
        }
    ],
    "uri": [
        {
            "value": "public:\/\/pictures\/2020-06\/photo_2020-06-05 19.31.47.jpeg"
        }
    ],
    "filemime": [
        {
            "value": "image\/jpeg"
        }
    ],
    "filesize": [
        {
            "value": 130061
        }
    ],
    "status": [
        {
            "value": true
        }
    ],
    "created": [
        {
            "value": "2020-06-05T23:33:12+00:00",
            "format": "Y-m-d\\TH:i:sP"
        }
    ],
    "changed": [
        {
            "value": "2020-06-05T23:33:18+00:00",
            "format": "Y-m-d\\TH:i:sP"
        }
    ]
}