{
    "uuid": [
        {
            "value": "b634524a-b7da-470b-a22c-3a340ae4c301"
        }
    ],
    "langcode": [
        {
            "value": "en"
        }
    ],
    "bundle": [
        {
            "value": "menu_link_content"
        }
    ],
    "revision_created": [
        {
            "value": "2020-05-18T06:35:38+00:00",
            "format": "Y-m-d\\TH:i:sP"
        }
    ],
    "revision_user": [],
    "revision_log_message": [],
    "enabled": [
        {
            "value": true
        }
    ],
    "title": [
        {
            "value": "Organizers and Volunteers"
        }
    ],
    "description": [],
    "menu_name": [
        {
            "value": "main"
        }
    ],
    "link": [
        {
            "uri": "entity:node\/c9412c89-d652-4690-b979-e1b5b13f6d80",
            "title": null,
            "options": []
        }
    ],
    "external": [
        {
            "value": false
        }
    ],
    "rediscover": [
        {
            "value": false
        }
    ],
    "weight": [
        {
            "value": -49
        }
    ],
    "expanded": [
        {
            "value": false
        }
    ],
    "parent": [
        {
            "value": "menu_link_content:2d94ba74-cf51-4543-aa1f-e2be47ac2922"
        }
    ],
    "changed": [
        {
            "value": "2020-05-18T07:13:31+00:00",
            "format": "Y-m-d\\TH:i:sP"
        }
    ],
    "default_langcode": [
        {
            "value": true
        }
    ],
    "revision_translation_affected": [
        {
            "value": true
        }
    ]
}