{
    "uid": [
        {
            "value": 56
        }
    ],
    "uuid": [
        {
            "value": "6ff7a70e-09c7-42fe-b9b2-4dcb48c0ba2d"
        }
    ],
    "langcode": [
        {
            "value": "en"
        }
    ],
    "preferred_langcode": [
        {
            "value": "en"
        }
    ],
    "preferred_admin_langcode": [
        {
            "value": "en"
        }
    ],
    "name": [
        {
            "value": "matthewm"
        }
    ],
    "mail": [],
    "timezone": [
        {
            "value": "America\/New_York"
        }
    ],
    "status": [
        {
            "value": true
        }
    ],
    "created": [
        {
            "value": "2020-11-11T18:53:01+00:00",
            "format": "Y-m-d\\TH:i:sP"
        }
    ],
    "changed": [
        {
            "value": "2020-11-11T18:53:01+00:00",
            "format": "Y-m-d\\TH:i:sP"
        }
    ],
    "roles": [],
    "default_langcode": [
        {
            "value": true
        }
    ],
    "path": [
        {
            "alias": null,
            "pid": null,
            "langcode": "en",
            "pathauto": 1
        }
    ],
    "field_dietary_intro": [],
    "field_interest_horizontal": [],
    "field_interest_vertical": [],
    "field_onsite_intro": [],
    "field_speaker": [
        {
            "value": "no"
        }
    ],
    "field_speaker_profile": [
        {
            "value": "<p>Matthew has a varied career being a front-end web developer, back-end application analyst and CMS engineer, and now doing Drupal development. He has worked at NewsAlert\/Inlumen, Marketwatch, Time Inc., and The Economist.<\/p>\r\n",
            "format": "basic_html"
        }
    ],
    "field_special_details": [],
    "field_ticket_orderno": [],
    "field_ticket_type": [],
    "field_u_acad_title_post": [],
    "field_u_acad_title_pre": [],
    "field_u_accessibility": [],
    "field_u_cat_mentor": [
        {
            "value": false
        }
    ],
    "field_u_cat_orgateam": [
        {
            "value": false
        }
    ],
    "field_u_cat_volunteer": [
        {
            "value": false
        }
    ],
    "field_u_childcare": [
        {
            "value": false
        }
    ],
    "field_u_company": [],
    "field_u_dietary": [],
    "field_u_first_name": [
        {
            "value": "Matthew"
        }
    ],
    "field_u_job_title": [],
    "field_u_last_name": [
        {
            "value": "Merkelson"
        }
    ],
    "field_u_middle_name": [],
    "field_u_pub_attendee_list": [
        {
            "value": true
        }
    ],
    "field_u_speaker_experience": [],
    "field_u_speaker_inclusion": [],
    "field_u_special_details": [],
    "field_u_testimonial": [],
    "field_u_volunteer_about": [],
    "user_picture": []
}