{
    "uid": [
        {
            "value": 0
        }
    ],
    "uuid": [
        {
            "value": "db0b5e60-a0b1-456f-8a9e-0e7441cecfd7"
        }
    ],
    "langcode": [
        {
            "value": "en"
        }
    ],
    "preferred_langcode": [
        {
            "value": "en"
        }
    ],
    "preferred_admin_langcode": [],
    "name": [
        {
            "value": ""
        }
    ],
    "mail": [],
    "timezone": [
        {
            "value": ""
        }
    ],
    "status": [
        {
            "value": false
        }
    ],
    "created": [
        {
            "value": "2020-05-08T18:29:37+00:00",
            "format": "Y-m-d\\TH:i:sP"
        }
    ],
    "changed": [
        {
            "value": "2020-05-08T18:29:37+00:00",
            "format": "Y-m-d\\TH:i:sP"
        }
    ],
    "roles": [],
    "default_langcode": [
        {
            "value": true
        }
    ],
    "path": [
        {
            "alias": null,
            "pid": null,
            "langcode": "en",
            "pathauto": 0
        }
    ],
    "field_dietary_intro": [],
    "field_interest_horizontal": [],
    "field_interest_vertical": [],
    "field_onsite_intro": [],
    "field_speaker": [],
    "field_speaker_profile": [],
    "field_special_details": [],
    "field_ticket_orderno": [],
    "field_ticket_type": [],
    "field_u_acad_title_post": [],
    "field_u_acad_title_pre": [],
    "field_u_accessibility": [],
    "field_u_cat_mentor": [],
    "field_u_cat_orgateam": [],
    "field_u_cat_volunteer": [],
    "field_u_childcare": [],
    "field_u_company": [],
    "field_u_dietary": [],
    "field_u_first_name": [],
    "field_u_job_title": [],
    "field_u_last_name": [],
    "field_u_middle_name": [],
    "field_u_pub_attendee_list": [],
    "field_u_speaker_experience": [],
    "field_u_speaker_inclusion": [],
    "field_u_special_details": [],
    "field_u_testimonial": [],
    "field_u_volunteer_about": [],
    "user_picture": []
}